athena2pyspark/__init__.py
athena2pyspark/test.py
athena2pyspark/config/__init__.py
athena2pyspark/graph/__init__.py
athena2pyspark/test/__init__.py
athena2pyspark/utils/__init__.py
athena2pyspark-0.0.3.dist-info/METADATA
athena2pyspark-0.0.3.dist-info/RECORD
athena2pyspark-0.0.3.dist-info/WHEEL
athena2pyspark-0.0.3.dist-info/top_level.txt
